irisml/tasks/launch_fiftyone.py
irisml_tasks_fiftyone-0.0.4.dist-info/LICENSE
irisml_tasks_fiftyone-0.0.4.dist-info/METADATA
irisml_tasks_fiftyone-0.0.4.dist-info/WHEEL
irisml_tasks_fiftyone-0.0.4.dist-info/top_level.txt
irisml_tasks_fiftyone-0.0.4.dist-info/RECORD
