Metadata-Version: 2.1
Name: irisml-tasks-fiftyone
Version: 0.0.4
Summary: IrisML tasks for fiftyone
Author: irisdev
License: MIT
Requires-Python: >=3.8
License-File: LICENSE
Requires-Dist: fiftyone ~=0.21
Requires-Dist: irisml
